statelogic/__init__.py
statelogic-1.1.0.dist-info/LICENSE
statelogic-1.1.0.dist-info/METADATA
statelogic-1.1.0.dist-info/WHEEL
statelogic-1.1.0.dist-info/top_level.txt
statelogic-1.1.0.dist-info/RECORD
