Metadata-Version: 2.1
Name: statelogic
Version: 1.1.0
Summary: A library for state management with colored messages
Home-page: https://github.com/Wilgat/Statelogic
Author: Wong Chun Fai
Author-email: wilgat.wong@gmail.com
Classifier: Programming Language :: Python :: 3
Classifier: License :: OSI Approved :: MIT License
Classifier: Operating System :: OS Independent
Requires-Python: >=3.6
License-File: LICENSE
